[
    {
        "id": 1,
        "title": "asd",
        "message": "asd",
        "timestamp": "2023-08-06 20:16:01.822201"
    },
    {
        "id": 2,
        "title": "ASDASDasd",
        "message": "asdasd",
        "timestamp": "2023-08-06 20:37:05.051893"
    },
    {
        "id": 3,
        "title": "<<<<ads",
        "message": "asdasddq2",
        "timestamp": "2023-08-06 20:37:19.342576"
    },
    {
        "id": 4,
        "title": "asdasdd12e",
        "message": "asDASDASD",
        "timestamp": "2023-08-06 20:37:29.528660"
    },
    {
        "id": 6,
        "title": "asd",
        "message": "asd",
        "timestamp": "2023-08-06 20:51:11.719314"
    },
    {
        "id": 7,
        "title": "ASDASD",
        "message": "asd",
        "timestamp": "2023-08-06 20:52:25.771718"
    },
    {
        "id": 8,
        "title": "mnbasdnbasdb",
        "message": "asdmnasnd",
        "timestamp": "2023-08-06 20:53:27.682066"
    },
    {
        "id": 9,
        "title": "lkj",
        "message": "asdm",
        "timestamp": "2023-08-06 20:55:48.028546"
    },
    {
        "id": 10,
        "title": "asd",
        "message": "ad",
        "timestamp": "2023-08-06 20:57:13.489110"
    }
]